botbuilder/schema/__init__.py
botbuilder/schema/_connector_client_enums.py
botbuilder/schema/_models_py3.py
botbuilder/schema/_sign_in_enums.py
botbuilder/schema/callerid_constants.py
botbuilder/schema/speech_constants.py
botbuilder/schema/teams/__init__.py
botbuilder/schema/teams/_models_py3.py
botbuilder/schema/teams/additional_properties.py
botbuilder_schema-4.15.1.dist-info/METADATA
botbuilder_schema-4.15.1.dist-info/WHEEL
botbuilder_schema-4.15.1.dist-info/top_level.txt
botbuilder_schema-4.15.1.dist-info/RECORD
