Metadata-Version: 2.1
Name: botbuilder-schema
Version: 4.15.1
Summary: BotBuilder Schema
Home-page: https://github.com/Microsoft/botbuilder-python
Author: Microsoft
License: MIT
Keywords: BotBuilderSchema,bots,ai,botframework,botbuilder
Platform: UNKNOWN
Classifier: Programming Language :: Python :: 3.7
Classifier: Intended Audience :: Developers
Classifier: License :: OSI Approved :: MIT License
Classifier: Operating System :: OS Independent
Classifier: Development Status :: 5 - Production/Stable
Classifier: Topic :: Scientific/Engineering :: Artificial Intelligence
Requires-Dist: msrest ==0.7.*
Requires-Dist: urllib3 <2.0.0
